smbd/__init__.py
smbd/systems.py
smbd/symbolic/__init__.py
smbd/symbolic/components/__init__.py
smbd/symbolic/components/algebraic_constraints.py
smbd/symbolic/components/bodies.py
smbd/symbolic/components/constraints_equations.py
smbd/symbolic/components/forces.py
smbd/symbolic/components/helpers.py
smbd/symbolic/components/joints.py
smbd/symbolic/components/matrices.py
smbd/symbolic/components/tests.py
smbd/symbolic/systems/__init__.py
smbd/symbolic/systems/configuration_classes.py
smbd/symbolic/systems/topology_classes.py
smbd/utilities/__init__.py
smbd/utilities/interfaces/__init__.py
smbd/utilities/interfaces/nbgens.py
smbd/utilities/interfaces/projects.py
smbd/utilities/interfaces/systems.py
smbd/utilities/serialization/__init__.py
smbd/utilities/serialization/structural/__init__.py
smbd/utilities/serialization/structural/json/__init__.py
smbd/utilities/serialization/structural/json/configuration_encoder.py
uraeus-0.0.dev1.dist-info/LICENSE
uraeus-0.0.dev1.dist-info/METADATA
uraeus-0.0.dev1.dist-info/WHEEL
uraeus-0.0.dev1.dist-info/top_level.txt
uraeus-0.0.dev1.dist-info/RECORD
