Metadata-Version: 2.1
Name: uraeus
Version: 0.0.dev1
Summary: Desc.
Home-page: https://github.com/khaledghobashy/uraeus
Author: Khaled Ghobashy
Author-email: khaled.ghobashy@live.com
License: UNKNOWN
Platform: UNKNOWN
Requires-Python: >=3.6
